semaphore_client/__init__.py
semaphore_client/api_client.py
semaphore_client/configuration.py
semaphore_client/rest.py
semaphore_client/semaphore_helper.py
semaphore_client/api/__init__.py
semaphore_client/api/authentication_api.py
semaphore_client/api/default_api.py
semaphore_client/api/project_api.py
semaphore_client/api/projects_api.py
semaphore_client/api/user_api.py
semaphore_client/models/__init__.py
semaphore_client/models/access_key.py
semaphore_client/models/access_key_request.py
semaphore_client/models/api_token.py
semaphore_client/models/body.py
semaphore_client/models/body1.py
semaphore_client/models/body2.py
semaphore_client/models/body3.py
semaphore_client/models/environment.py
semaphore_client/models/environment_request.py
semaphore_client/models/event.py
semaphore_client/models/info_type.py
semaphore_client/models/info_type_update.py
semaphore_client/models/inventory.py
semaphore_client/models/inventory_request.py
semaphore_client/models/login.py
semaphore_client/models/password.py
semaphore_client/models/pong.py
semaphore_client/models/project.py
semaphore_client/models/project1.py
semaphore_client/models/project_request.py
semaphore_client/models/repository.py
semaphore_client/models/repository_request.py
semaphore_client/models/task.py
semaphore_client/models/task_output.py
semaphore_client/models/template.py
semaphore_client/models/template_request.py
semaphore_client/models/user.py
semaphore_client/models/user1.py
semaphore_client/models/user_request.py
test/__init__.py
test/test_access_key.py
test/test_access_key_request.py
test/test_api_token.py
test/test_authentication_api.py
test/test_default_api.py
test/test_environment.py
test/test_environment_request.py
test/test_event.py
test/test_get_repository.py
test/test_helper.py
test/test_info_type.py
test/test_info_type_update.py
test/test_inventory.py
test/test_inventory_request.py
test/test_login.py
test/test_password.py
test/test_pong.py
test/test_project.py
test/test_project1.py
semaphore_client-1.0.0.dist-info/METADATA
semaphore_client-1.0.0.dist-info/WHEEL
semaphore_client-1.0.0.dist-info/top_level.txt
semaphore_client-1.0.0.dist-info/RECORD
