Metadata-Version: 2.1
Name: semaphore-client
Version: 1.0.0
Summary: SEMAPHORE
Home-page: https://github.com/QCDIS/semaphore-python-client
Author: UNKNOWN
Author-email: S.Koulouzis@uva.nl
License: UNKNOWN
Keywords: Swagger,SEMAPHORE
Platform: UNKNOWN
Classifier: Programming Language :: Python :: 3
Classifier: License :: OSI Approved :: Apache Software License
Classifier: Operating System :: OS Independent
Requires-Dist: certifi (==2020.4.5.1)
Requires-Dist: six (==1.14.0)
Requires-Dist: urllib3 (==1.25.8)
Requires-Dist: setuptools (==46.1.3)
